{
  "ComponentIndexes": {
    "Component1": 13
  },
  "ControlUniqueGuids": {},
  "ControlUniqueIds": {
    "AboutDescription": 175,
    "AboutDescription_1": 198,
    "AboutLeaveGallerySeparator": 183,
    "AboutLeaveGallerySeparator_1": 206,
    "AboutLeaveMiddle": 184,
    "AboutLeaveMiddle_1": 207,
    "AboutLeaveTypeButton": 180,
    "AboutLeaveTypeButton_1": 203,
    "AboutLeaveTypeDescription": 182,
    "AboutLeaveTypeDescription_1": 205,
    "AboutLeaveTypeGallery": 177,
    "AboutLeaveTypeGallery_1": 200,
    "AboutLeaveTypeLabel": 181,
    "AboutLeaveTypeLabel_1": 204,
    "AboutLeveTypeCell": 179,
    "AboutLeveTypeCell_1": 202,
    "AboutScreen": 163,
    "AboutScreenManager": 186,
    "AboutTitle": 176,
    "AboutTitle_1": 199,
    "App": 1,
    "ApproverComments_DataCard1": 138,
    "BackIcon_1": 100,
    "BackIcon_2": 147,
    "Button1": 28,
    "Button1_1": 275,
    "Button1_2": 58,
    "Button1_3": 87,
    "Button2": 250,
    "Button2_1": 253,
    "Button3": 143,
    "Button4": 23,
    "Button4_1": 265,
    "Button4_2": 53,
    "Button4_3": 82,
    "Cancel_1": 98,
    "Circle1": 12,
    "Circle1_1": 234,
    "Circle1_2": 287,
    "Circle1_3": 170,
    "Circle1_4": 216,
    "Circle1_5": 193,
    "Circle1_6": 40,
    "Circle1_7": 75,
    "CompanyHolidaysManager": 209,
    "CompanyHolidaysScreen": 227,
    "Component1": 4,
    "Container1": 6,
    "Container1_1": 164,
    "Container1_2": 281,
    "Container1_3": 228,
    "Container1_4": 255,
    "Container1_5": 210,
    "Container1_6": 187,
    "Container1_7": 34,
    "Container1_8": 69,
    "Container2": 247,
    "Container3": 248,
    "Container3_1": 251,
    "Container4": 17,
    "Container4_2": 266,
    "Created By_DataCard1": 125,
    "Created_DataCard1": 130,
    "DataCard5": 123,
    "DataCardKey1": 140,
    "DataCardKey1_1": 153,
    "DataCardKey10": 115,
    "DataCardKey12": 120,
    "DataCardKey2": 131,
    "DataCardKey3": 127,
    "DataCardKey3_1": 157,
    "DataCardKey5": 135,
    "DataCardKey5_1": 149,
    "DataCardKey6_1": 150,
    "DataCardKey7": 105,
    "DataCardKey8_1": 155,
    "DataCardKey9": 110,
    "DataCardValue1": 141,
    "DataCardValue1_2": 156,
    "DataCardValue1_3": 158,
    "DataCardValue10": 116,
    "DataCardValue12": 121,
    "DataCardValue2": 132,
    "DataCardValue3": 128,
    "DataCardValue5": 136,
    "DataCardValue5_1": 151,
    "DataCardValue6_1": 152,
    "DataCardValue7": 106,
    "DataCardValue9": 111,
    "Dropdown1": 154,
    "Dropdown2": 302,
    "EndDate_DataCard2": 113,
    "ErrorMessage1": 142,
    "ErrorMessage11": 117,
    "ErrorMessage13": 122,
    "ErrorMessage2": 129,
    "ErrorMessage5": 137,
    "ErrorMessage6": 107,
    "ErrorMessage9": 112,
    "Form3": 102,
    "Gallery1": 21,
    "Gallery1_1": 263,
    "Gallery1_2": 271,
    "Gallery1_3": 51,
    "Gallery1_4": 80,
    "Gallery2": 240,
    "Gallery2_1": 222,
    "Gallery3_10": 77,
    "Gallery3_2": 236,
    "Gallery3_3": 172,
    "Gallery3_4": 260,
    "Gallery3_5": 218,
    "Gallery3_6": 195,
    "Gallery3_7": 289,
    "Gallery3_8": 14,
    "Gallery3_9": 42,
    "Gallery4": 24,
    "Gallery4_1": 54,
    "Gallery4_2": 83,
    "GalleryLeaveBalance": 293,
    "GalleryLeaveBalance_1": 45,
    "GalleryLeaveBalance_2": 64,
    "galleryTemplate1": 22,
    "galleryTemplate1_1": 264,
    "galleryTemplate1_2": 272,
    "galleryTemplate1_3": 52,
    "galleryTemplate1_4": 81,
    "galleryTemplate2": 241,
    "galleryTemplate2_1": 223,
    "galleryTemplate2_10": 201,
    "galleryTemplate2_9": 178,
    "galleryTemplate3_10": 78,
    "galleryTemplate3_2": 237,
    "galleryTemplate3_3": 173,
    "galleryTemplate3_4": 261,
    "galleryTemplate3_5": 219,
    "galleryTemplate3_6": 196,
    "galleryTemplate3_7": 290,
    "galleryTemplate3_8": 15,
    "galleryTemplate3_9": 43,
    "galleryTemplate4": 25,
    "galleryTemplate4_1": 55,
    "galleryTemplate4_2": 84,
    "galleryTemplate8": 294,
    "galleryTemplate8_1": 46,
    "galleryTemplate8_2": 65,
    "Group1": 32,
    "Group1_1": 300,
    "Group1_2": 244,
    "Group1_3": 185,
    "Group1_4": 226,
    "Group1_5": 208,
    "Group1_6": 62,
    "Group1_7": 91,
    "Group2": 11,
    "Group2_1": 286,
    "Group2_2": 233,
    "Group2_3": 169,
    "Group2_4": 259,
    "Group2_5": 215,
    "Group2_6": 192,
    "Group2_7": 39,
    "Group2_8": 74,
    "Header_1": 144,
    "Header_2": 161,
    "Host": 3,
    "Icon1": 301,
    "icon2": 9,
    "Icon2": 13,
    "icon2_1": 168,
    "Icon2_1": 235,
    "icon2_2": 285,
    "Icon2_2": 288,
    "icon2_3": 232,
    "Icon2_3": 171,
    "icon2_4": 258,
    "Icon2_4": 217,
    "icon2_5": 214,
    "Icon2_5": 194,
    "icon2_6": 191,
    "Icon2_6": 41,
    "icon2_7": 37,
    "Icon2_7": 76,
    "icon2_8": 72,
    "icon3": 296,
    "Icon3": 30,
    "icon3_1": 49,
    "Icon3_1": 60,
    "Icon3_2": 89,
    "Icon5": 278,
    "Image1": 246,
    "Image2": 18,
    "Image3": 274,
    "Label1": 249,
    "Label1_1": 252,
    "Label10": 26,
    "Label10_1": 29,
    "Label10_2": 31,
    "Label10_3": 56,
    "Label10_4": 59,
    "Label10_5": 61,
    "Label10_6": 85,
    "Label10_7": 88,
    "Label10_8": 90,
    "Label11": 276,
    "Label12": 19,
    "Label13": 20,
    "Label14": 277,
    "Label16": 297,
    "Label16_1": 48,
    "Label16_2": 67,
    "Label17": 298,
    "Label17_1": 50,
    "Label17_2": 68,
    "Label18": 299,
    "Label2": 292,
    "Label2_1": 96,
    "Label2_2": 273,
    "Label2_4": 279,
    "Label3": 239,
    "Label3_1": 221,
    "Label4": 27,
    "Label4_1": 57,
    "Label4_10": 269,
    "Label4_11": 268,
    "Label4_2": 86,
    "Label4_7": 270,
    "Label4_9": 267,
    "Label5": 242,
    "Label5_1": 243,
    "Label5_2": 224,
    "Label5_3": 225,
    "Label6": 124,
    "Label9_10": 79,
    "Label9_2": 238,
    "Label9_3": 174,
    "Label9_4": 262,
    "Label9_5": 220,
    "Label9_6": 197,
    "Label9_7": 291,
    "Label9_8": 16,
    "Label9_9": 44,
    "LblHeaderCreateNew": 10,
    "LblHeaderCreateNew_1": 167,
    "LblHeaderCreateNew_2": 284,
    "LblHeaderCreateNew_3": 231,
    "LblHeaderCreateNew_4": 213,
    "LblHeaderCreateNew_5": 190,
    "LblHeaderCreateNew_6": 38,
    "LblHeaderCreateNew_7": 73,
    "LblHeaderTItle1": 7,
    "LblHeaderTItle1_1": 8,
    "LblHeaderTItle1_10": 211,
    "LblHeaderTItle1_11": 212,
    "LblHeaderTItle1_12": 188,
    "LblHeaderTItle1_13": 189,
    "LblHeaderTItle1_14": 35,
    "LblHeaderTItle1_15": 36,
    "LblHeaderTItle1_16": 70,
    "LblHeaderTItle1_17": 71,
    "LblHeaderTItle1_2": 165,
    "LblHeaderTItle1_3": 166,
    "LblHeaderTItle1_4": 282,
    "LblHeaderTItle1_5": 283,
    "LblHeaderTItle1_6": 229,
    "LblHeaderTItle1_7": 230,
    "LblHeaderTItle1_8": 256,
    "LblHeaderTItle1_9": 257,
    "LeaveDescription_DataCard2": 118,
    "LeaveStatus_DataCard2": 133,
    "LeaveType_DataCard2": 103,
    "LoginScreen": 245,
    "ManagerRequests": 254,
    "MyLeaveBalance": 280,
    "MyLeaveRequests": 5,
    "MyLeaveRequests_1": 33,
    "MyLeaveRequests_2": 63,
    "NewExpenseCancelButton_1": 159,
    "NewExpenseCreateButton_2": 160,
    "NewRequestLabel_1": 101,
    "NewRequestLabel_2": 148,
    "NewRequests_1": 92,
    "Popup Confirmation_1": 94,
    "popup rectangle_1": 99,
    "Rectangle1_1": 93,
    "Rectangle1_2": 146,
    "Rectangle2_1": 95,
    "Rectangle6": 295,
    "Rectangle6_1": 47,
    "Rectangle6_2": 66,
    "Screen1": 145,
    "Screen2": 162,
    "StartDate_DataCard2": 108,
    "StarVisible1": 139,
    "StarVisible11": 114,
    "StarVisible13": 119,
    "StarVisible2": 126,
    "StarVisible5": 134,
    "StarVisible6": 104,
    "StarVisible9": 109,
    "SubmitForm_1": 97
  },
  "FunctionParamsInvariantScripts": {},
  "FunctionParamsInvariantScriptsOnInstances": {},
  "HeaderLastSavedDateTimeUTC": "11/06/2023 18:35:30",
  "IsLegacyComponentAllowGlobalScopeCase": false,
  "LocalConnectionIDReferences": {
    "0eaccec2-7e15-4a0c-beab-536112d3679b": "\"/providers/microsoft.powerapps/apis/shared_sharepointonline/connections/bb0db7aed4f34824afc6e3e638b8ff5f\"",
    "339d001c-68f8-451d-bd49-e53ec7d1d9cd": "\"/providers/microsoft.powerapps/apis/shared_sharepointonline/connections/bb0db7aed4f34824afc6e3e638b8ff5f\"",
    "44324c75-91ed-4c3c-b7b9-f54b1e15ae09": "\"/providers/microsoft.powerapps/apis/shared_sharepointonline/connections/bb0db7aed4f34824afc6e3e638b8ff5f\"",
    "7d0d7931-4e22-473e-8751-3541255a0e62": "\"/providers/microsoft.powerapps/apis/shared_office365/connections/shared-office365-5c090cb2-a75c-4589-8e3a-80a450d7ee5c\"",
    "e04c1bef-7a64-4c1e-aca8-dc4f9e575fae": "\"/providers/microsoft.powerapps/apis/shared_logicflows/connections/0e861c6f53127f023b292c0337304325-c5e99a05de15fd0e\"",
    "ea3fee7f-88e6-4ddc-808f-fb01933c5e21": "\"/providers/microsoft.powerapps/apis/shared_sharepointonline/connections/bb0db7aed4f34824afc6e3e638b8ff5f\""
  },
  "LocalDatabaseReferencesAsEmpty": false,
  "LocalResourceFileNames": {
    "IMAGE1": "0001.PNG",
    "image2": "0002.png",
    "LMS": "0003.png"
  },
  "LocalResourceRootPaths": {
    "IMAGE1": "https://docserverpwaprodeus.blob.core.windows.net/61e4853c-2b86-4a17-ae89-77b6754202fe-1/resource/Assets0Images00001.PNG?skoid=58690ece-ec83-4ce2-9ce8-883d4d6a54ee&sktid=975f013f-7f24-47e8-a7d3-abc4752bf346&skt=2023-11-06T18%3A18%3A52Z&ske=2023-11-07T18%3A33%3A52Z&sks=b&skv=2021-12-02&sv=2021-12-02&spr=https&se=2023-11-07T18%3A33%3A52Z&sr=b&sp=r&sig=DQI2RyM2quc5IPdjONXrVpjFZjKmZYlHufwBOT2LeoY%3D",
    "image2": "https://docserverpwaprodeus.blob.core.windows.net/61e4853c-2b86-4a17-ae89-77b6754202fe-1/resource/Assets0Images00002.png?skoid=58690ece-ec83-4ce2-9ce8-883d4d6a54ee&sktid=975f013f-7f24-47e8-a7d3-abc4752bf346&skt=2023-11-06T18%3A18%3A52Z&ske=2023-11-07T18%3A33%3A52Z&sks=b&skv=2021-12-02&sv=2021-12-02&spr=https&se=2023-11-07T18%3A33%3A52Z&sr=b&sp=r&sig=JQ4phFIVaduaCz9Tg%2BBJHx8MBuBdoP9JDwqRMFlFf3E%3D",
    "LMS": "https://docserverpwaprodeus.blob.core.windows.net/61e4853c-2b86-4a17-ae89-77b6754202fe-1/resource/Assets0Images00003.png?skoid=58690ece-ec83-4ce2-9ce8-883d4d6a54ee&sktid=975f013f-7f24-47e8-a7d3-abc4752bf346&skt=2023-11-06T18%3A18%3A52Z&ske=2023-11-07T18%3A33%3A52Z&sks=b&skv=2021-12-02&sv=2021-12-02&spr=https&se=2023-11-07T18%3A33%3A52Z&sr=b&sp=r&sig=GUODX8gCj3GQLZ7rjWFIPEKxzHjG9QrUuBbVHGSi1tI%3D"
  },
  "OrderComponentMetadata": {
    "9c778db04d854105b4af47ae39f6462e": 0
  },
  "OrderComponentTemplate": {
    "9c778db04d854105b4af47ae39f6462e": 0
  },
  "OrderDataSource": {
    "ComboBoxSample": 2,
    "CompanyHolidays": 7,
    "CustomGallerySample": 3,
    "DropDownSample": 4,
    "EmployeeNav": 8,
    "LeaveBalance": 9,
    "LeaveRequestsList": 5,
    "LeaveTypeCollection": 10,
    "LRequests": 6,
    "ManagerViewNav": 11,
    "Office365Outlook": 0,
    "RequestsFlow": 1
  },
  "OrderGroupControls": {
    "AboutLeaveMiddle": {
      "AboutDescription": 2,
      "AboutLeaveGallerySeparator": 4,
      "AboutLeaveTypeDescription": 3,
      "AboutLeaveTypeGallery": 1,
      "AboutTitle": 0
    },
    "AboutLeaveMiddle_1": {
      "AboutDescription_1": 2,
      "AboutLeaveGallerySeparator_1": 4,
      "AboutLeaveTypeDescription_1": 3,
      "AboutLeaveTypeGallery_1": 1,
      "AboutTitle_1": 0
    },
    "Group1": {
      "Circle1": 0,
      "Icon2": 1
    },
    "Group1_1": {
      "Circle1_2": 0,
      "Icon2_2": 1
    },
    "Group1_2": {
      "Circle1_1": 0,
      "Icon2_1": 1
    },
    "Group1_3": {
      "Circle1_3": 0,
      "Icon2_3": 1
    },
    "Group1_4": {
      "Circle1_4": 0,
      "Icon2_4": 1
    },
    "Group1_5": {
      "Circle1_5": 0,
      "Icon2_5": 1
    },
    "Group1_6": {
      "Circle1_6": 0,
      "Icon2_6": 1
    },
    "Group1_7": {
      "Circle1_7": 0,
      "Icon2_7": 1
    },
    "Group2": {
      "icon2": 1,
      "LblHeaderTItle1": 0,
      "LblHeaderTItle1_1": 2
    },
    "Group2_1": {
      "icon2_2": 1,
      "LblHeaderTItle1_4": 0,
      "LblHeaderTItle1_5": 2
    },
    "Group2_2": {
      "icon2_3": 1,
      "LblHeaderTItle1_6": 0,
      "LblHeaderTItle1_7": 2
    },
    "Group2_3": {
      "icon2_1": 1,
      "LblHeaderTItle1_2": 0,
      "LblHeaderTItle1_3": 2
    },
    "Group2_4": {
      "icon2_4": 1,
      "LblHeaderTItle1_8": 0,
      "LblHeaderTItle1_9": 2
    },
    "Group2_5": {
      "icon2_5": 1,
      "LblHeaderTItle1_10": 0,
      "LblHeaderTItle1_11": 2
    },
    "Group2_6": {
      "icon2_6": 1,
      "LblHeaderTItle1_12": 0,
      "LblHeaderTItle1_13": 2
    },
    "Group2_7": {
      "icon2_7": 1,
      "LblHeaderTItle1_14": 0,
      "LblHeaderTItle1_15": 2
    },
    "Group2_8": {
      "icon2_8": 1,
      "LblHeaderTItle1_16": 0,
      "LblHeaderTItle1_17": 2
    },
    "Header_1": {
      "BackIcon_1": 2,
      "NewRequestLabel_1": 1,
      "Rectangle1_1": 0
    },
    "Header_2": {
      "BackIcon_2": 2,
      "NewRequestLabel_2": 1,
      "Rectangle1_2": 0
    },
    "popup rectangle_1": {
      "Cancel_1": 3,
      "Label2_1": 1,
      "Rectangle2_1": 0,
      "SubmitForm_1": 2
    }
  },
  "OrderPcfTemplate": {},
  "OrderTemplate": {},
  "OrderXMLTemplate": {
    "button": 6,
    "circle": 3,
    "combobox": 10,
    "datepicker": 11,
    "dropdown": 8,
    "form": 9,
    "gallery": 4,
    "groupContainer": 0,
    "icon": 2,
    "image": 5,
    "label": 1,
    "rectangle": 7,
    "text": 12
  },
  "OverridablePropertiesEntry": {
    "AboutDescription": {},
    "AboutDescription_1": {},
    "AboutLeaveGallerySeparator": {},
    "AboutLeaveGallerySeparator_1": {},
    "AboutLeaveMiddle": {},
    "AboutLeaveMiddle_1": {},
    "AboutLeaveTypeButton": {},
    "AboutLeaveTypeButton_1": {},
    "AboutLeaveTypeDescription": {},
    "AboutLeaveTypeDescription_1": {},
    "AboutLeaveTypeGallery": {},
    "AboutLeaveTypeGallery_1": {},
    "AboutLeaveTypeLabel": {},
    "AboutLeaveTypeLabel_1": {},
    "AboutLeveTypeCell": {},
    "AboutLeveTypeCell_1": {},
    "AboutScreen": {},
    "AboutScreenManager": {},
    "AboutTitle": {},
    "AboutTitle_1": {},
    "App": {},
    "ApproverComments_DataCard1": {},
    "BackIcon_1": {},
    "BackIcon_2": {},
    "Button1": {},
    "Button1_1": {},
    "Button1_2": {},
    "Button1_3": {},
    "Button2": {},
    "Button2_1": {},
    "Button3": {},
    "Button4": {},
    "Button4_1": {},
    "Button4_2": {},
    "Button4_3": {},
    "Cancel_1": {},
    "Circle1": {},
    "Circle1_1": {},
    "Circle1_2": {},
    "Circle1_3": {},
    "Circle1_4": {},
    "Circle1_5": {},
    "Circle1_6": {},
    "Circle1_7": {},
    "CompanyHolidaysManager": {},
    "CompanyHolidaysScreen": {},
    "Component1": {},
    "Container1": {},
    "Container1_1": {},
    "Container1_2": {},
    "Container1_3": {},
    "Container1_4": {},
    "Container1_5": {},
    "Container1_6": {},
    "Container1_7": {},
    "Container1_8": {},
    "Container2": {},
    "Container3": {},
    "Container3_1": {},
    "Container4": {},
    "Container4_2": {},
    "Created By_DataCard1": {},
    "Created_DataCard1": {},
    "DataCard5": {},
    "DataCardKey1": {},
    "DataCardKey1_1": {},
    "DataCardKey10": {},
    "DataCardKey12": {},
    "DataCardKey2": {},
    "DataCardKey3": {},
    "DataCardKey3_1": {},
    "DataCardKey5": {},
    "DataCardKey5_1": {},
    "DataCardKey6_1": {},
    "DataCardKey7": {},
    "DataCardKey8_1": {},
    "DataCardKey9": {},
    "DataCardValue1": {},
    "DataCardValue1_2": {},
    "DataCardValue1_3": {},
    "DataCardValue10": {},
    "DataCardValue12": {},
    "DataCardValue2": {},
    "DataCardValue3": {},
    "DataCardValue5": {},
    "DataCardValue5_1": {},
    "DataCardValue6_1": {},
    "DataCardValue7": {},
    "DataCardValue9": {},
    "Dropdown1": {},
    "Dropdown2": {},
    "EndDate_DataCard2": {},
    "ErrorMessage1": {},
    "ErrorMessage11": {},
    "ErrorMessage13": {},
    "ErrorMessage2": {},
    "ErrorMessage5": {},
    "ErrorMessage6": {},
    "ErrorMessage9": {},
    "Form3": {},
    "Gallery1": {},
    "Gallery1_1": {},
    "Gallery1_2": {},
    "Gallery1_3": {},
    "Gallery1_4": {},
    "Gallery2": {},
    "Gallery2_1": {},
    "Gallery3_10": {},
    "Gallery3_2": {},
    "Gallery3_3": {},
    "Gallery3_4": {},
    "Gallery3_5": {},
    "Gallery3_6": {},
    "Gallery3_7": {},
    "Gallery3_8": {},
    "Gallery3_9": {},
    "Gallery4": {},
    "Gallery4_1": {},
    "Gallery4_2": {},
    "GalleryLeaveBalance": {},
    "GalleryLeaveBalance_1": {},
    "GalleryLeaveBalance_2": {},
    "galleryTemplate1": {},
    "galleryTemplate1_1": {},
    "galleryTemplate1_2": {},
    "galleryTemplate1_3": {},
    "galleryTemplate1_4": {},
    "galleryTemplate2": {},
    "galleryTemplate2_1": {},
    "galleryTemplate2_10": {},
    "galleryTemplate2_9": {},
    "galleryTemplate3_10": {},
    "galleryTemplate3_2": {},
    "galleryTemplate3_3": {},
    "galleryTemplate3_4": {},
    "galleryTemplate3_5": {},
    "galleryTemplate3_6": {},
    "galleryTemplate3_7": {},
    "galleryTemplate3_8": {},
    "galleryTemplate3_9": {},
    "galleryTemplate4": {},
    "galleryTemplate4_1": {},
    "galleryTemplate4_2": {},
    "galleryTemplate8": {},
    "galleryTemplate8_1": {},
    "galleryTemplate8_2": {},
    "Group1": {},
    "Group1_1": {},
    "Group1_2": {},
    "Group1_3": {},
    "Group1_4": {},
    "Group1_5": {},
    "Group1_6": {},
    "Group1_7": {},
    "Group2": {},
    "Group2_1": {},
    "Group2_2": {},
    "Group2_3": {},
    "Group2_4": {},
    "Group2_5": {},
    "Group2_6": {},
    "Group2_7": {},
    "Group2_8": {},
    "Header_1": {},
    "Header_2": {},
    "Host": {},
    "Icon1": {},
    "icon2": {},
    "Icon2": {},
    "icon2_1": {},
    "Icon2_1": {},
    "icon2_2": {},
    "Icon2_2": {},
    "icon2_3": {},
    "Icon2_3": {},
    "icon2_4": {},
    "Icon2_4": {},
    "icon2_5": {},
    "Icon2_5": {},
    "icon2_6": {},
    "Icon2_6": {},
    "icon2_7": {},
    "Icon2_7": {},
    "icon2_8": {},
    "icon3": {},
    "Icon3": {},
    "icon3_1": {},
    "Icon3_1": {},
    "Icon3_2": {},
    "Icon5": {},
    "Image1": {},
    "Image2": {},
    "Image3": {},
    "Label1": {},
    "Label1_1": {},
    "Label10": {},
    "Label10_1": {},
    "Label10_2": {},
    "Label10_3": {},
    "Label10_4": {},
    "Label10_5": {},
    "Label10_6": {},
    "Label10_7": {},
    "Label10_8": {},
    "Label11": {},
    "Label12": {},
    "Label13": {},
    "Label14": {},
    "Label16": {},
    "Label16_1": {},
    "Label16_2": {},
    "Label17": {},
    "Label17_1": {},
    "Label17_2": {},
    "Label18": {},
    "Label2": {},
    "Label2_1": {},
    "Label2_2": {},
    "Label2_4": {},
    "Label3": {},
    "Label3_1": {},
    "Label4": {},
    "Label4_1": {},
    "Label4_10": {},
    "Label4_11": {},
    "Label4_2": {},
    "Label4_7": {},
    "Label4_9": {},
    "Label5": {},
    "Label5_1": {},
    "Label5_2": {},
    "Label5_3": {},
    "Label6": {},
    "Label9_10": {},
    "Label9_2": {},
    "Label9_3": {},
    "Label9_4": {},
    "Label9_5": {},
    "Label9_6": {},
    "Label9_7": {},
    "Label9_8": {},
    "Label9_9": {},
    "LblHeaderCreateNew": {},
    "LblHeaderCreateNew_1": {},
    "LblHeaderCreateNew_2": {},
    "LblHeaderCreateNew_3": {},
    "LblHeaderCreateNew_4": {},
    "LblHeaderCreateNew_5": {},
    "LblHeaderCreateNew_6": {},
    "LblHeaderCreateNew_7": {},
    "LblHeaderTItle1": {},
    "LblHeaderTItle1_1": {},
    "LblHeaderTItle1_10": {},
    "LblHeaderTItle1_11": {},
    "LblHeaderTItle1_12": {},
    "LblHeaderTItle1_13": {},
    "LblHeaderTItle1_14": {},
    "LblHeaderTItle1_15": {},
    "LblHeaderTItle1_16": {},
    "LblHeaderTItle1_17": {},
    "LblHeaderTItle1_2": {},
    "LblHeaderTItle1_3": {},
    "LblHeaderTItle1_4": {},
    "LblHeaderTItle1_5": {},
    "LblHeaderTItle1_6": {},
    "LblHeaderTItle1_7": {},
    "LblHeaderTItle1_8": {},
    "LblHeaderTItle1_9": {},
    "LeaveDescription_DataCard2": {},
    "LeaveStatus_DataCard2": {},
    "LeaveType_DataCard2": {},
    "LoginScreen": {},
    "ManagerRequests": {},
    "MyLeaveBalance": {},
    "MyLeaveRequests": {},
    "MyLeaveRequests_1": {},
    "MyLeaveRequests_2": {},
    "NewExpenseCancelButton_1": {},
    "NewExpenseCreateButton_2": {},
    "NewRequestLabel_1": {},
    "NewRequestLabel_2": {},
    "NewRequests_1": {},
    "Popup Confirmation_1": {},
    "popup rectangle_1": {},
    "Rectangle1_1": {},
    "Rectangle1_2": {},
    "Rectangle2_1": {},
    "Rectangle6": {},
    "Rectangle6_1": {},
    "Rectangle6_2": {},
    "Screen1": {},
    "Screen2": {},
    "StartDate_DataCard2": {},
    "StarVisible1": {},
    "StarVisible11": {},
    "StarVisible13": {},
    "StarVisible2": {},
    "StarVisible5": {},
    "StarVisible6": {},
    "StarVisible9": {},
    "SubmitForm_1": {}
  },
  "PCFDynamicSchemaForIRRetrievalEntry": {},
  "PCFTemplateEntry": {},
  "PublishOrderIndices": {
    "AboutDescription": 115,
    "AboutDescription_1": 231,
    "AboutLeaveGallerySeparator": 123,
    "AboutLeaveGallerySeparator_1": 239,
    "AboutLeaveMiddle": 102,
    "AboutLeaveMiddle_1": 218,
    "AboutLeaveTypeButton": 120,
    "AboutLeaveTypeButton_1": 236,
    "AboutLeaveTypeDescription": 122,
    "AboutLeaveTypeDescription_1": 238,
    "AboutLeaveTypeGallery": 117,
    "AboutLeaveTypeGallery_1": 233,
    "AboutLeaveTypeLabel": 121,
    "AboutLeaveTypeLabel_1": 237,
    "AboutLeveTypeCell": 119,
    "AboutLeveTypeCell_1": 235,
    "AboutScreen": 2,
    "AboutScreenManager": 25,
    "AboutTitle": 116,
    "AboutTitle_1": 232,
    "App": 0,
    "ApproverComments_DataCard1": 212,
    "BackIcon_1": 173,
    "BackIcon_2": 241,
    "Button1": 31,
    "Button1_1": 161,
    "Button1_2": 281,
    "Button1_3": 61,
    "Button2": 4,
    "Button2_1": 7,
    "Button3": 217,
    "Button4": 26,
    "Button4_1": 151,
    "Button4_2": 276,
    "Button4_3": 56,
    "Cancel_1": 172,
    "Circle1": 14,
    "Circle1_1": 130,
    "Circle1_2": 88,
    "Circle1_3": 109,
    "Circle1_4": 71,
    "Circle1_5": 225,
    "Circle1_6": 262,
    "Circle1_7": 41,
    "CompanyHolidaysManager": 50,
    "CompanyHolidaysScreen": 68,
    "Component1": 1,
    "Container1": 8,
    "Container1_1": 103,
    "Container1_2": 82,
    "Container1_3": 124,
    "Container1_4": 141,
    "Container1_5": 65,
    "Container1_6": 219,
    "Container1_7": 256,
    "Container1_8": 35,
    "Container2": 1,
    "Container3": 2,
    "Container3_1": 5,
    "Container4": 20,
    "Container4_2": 152,
    "Created By_DataCard1": 199,
    "Created_DataCard1": 204,
    "DataCard5": 197,
    "DataCardKey1": 214,
    "DataCardKey1_1": 248,
    "DataCardKey10": 189,
    "DataCardKey12": 194,
    "DataCardKey2": 205,
    "DataCardKey3": 201,
    "DataCardKey3_1": 252,
    "DataCardKey5": 209,
    "DataCardKey5_1": 244,
    "DataCardKey6_1": 245,
    "DataCardKey7": 179,
    "DataCardKey8_1": 250,
    "DataCardKey9": 184,
    "DataCardValue1": 215,
    "DataCardValue1_2": 251,
    "DataCardValue1_3": 253,
    "DataCardValue10": 190,
    "DataCardValue12": 195,
    "DataCardValue2": 206,
    "DataCardValue3": 202,
    "DataCardValue5": 210,
    "DataCardValue5_1": 246,
    "DataCardValue6_1": 247,
    "DataCardValue7": 180,
    "DataCardValue9": 185,
    "Dropdown1": 249,
    "Dropdown2": 53,
    "EndDate_DataCard2": 187,
    "ErrorMessage1": 216,
    "ErrorMessage11": 191,
    "ErrorMessage13": 196,
    "ErrorMessage2": 203,
    "ErrorMessage5": 211,
    "ErrorMessage6": 181,
    "ErrorMessage9": 186,
    "Form3": 176,
    "Gallery1": 24,
    "Gallery1_1": 149,
    "Gallery1_2": 157,
    "Gallery1_3": 274,
    "Gallery1_4": 54,
    "Gallery2": 137,
    "Gallery2_1": 78,
    "Gallery3_10": 44,
    "Gallery3_2": 133,
    "Gallery3_3": 112,
    "Gallery3_4": 146,
    "Gallery3_5": 74,
    "Gallery3_6": 228,
    "Gallery3_7": 91,
    "Gallery3_8": 17,
    "Gallery3_9": 265,
    "Gallery4": 27,
    "Gallery4_1": 277,
    "Gallery4_2": 57,
    "GalleryLeaveBalance": 95,
    "GalleryLeaveBalance_1": 268,
    "GalleryLeaveBalance_2": 47,
    "galleryTemplate1": 25,
    "galleryTemplate1_1": 150,
    "galleryTemplate1_2": 158,
    "galleryTemplate1_3": 275,
    "galleryTemplate1_4": 55,
    "galleryTemplate2": 138,
    "galleryTemplate2_1": 79,
    "galleryTemplate2_10": 234,
    "galleryTemplate2_9": 118,
    "galleryTemplate3_10": 45,
    "galleryTemplate3_2": 134,
    "galleryTemplate3_3": 113,
    "galleryTemplate3_4": 147,
    "galleryTemplate3_5": 75,
    "galleryTemplate3_6": 229,
    "galleryTemplate3_7": 92,
    "galleryTemplate3_8": 18,
    "galleryTemplate3_9": 266,
    "galleryTemplate4": 28,
    "galleryTemplate4_1": 278,
    "galleryTemplate4_2": 58,
    "galleryTemplate8": 96,
    "galleryTemplate8_1": 269,
    "galleryTemplate8_2": 48,
    "Group1": 15,
    "Group1_1": 90,
    "Group1_2": 132,
    "Group1_3": 111,
    "Group1_4": 73,
    "Group1_5": 227,
    "Group1_6": 264,
    "Group1_7": 42,
    "Group2": 11,
    "Group2_1": 87,
    "Group2_2": 129,
    "Group2_3": 108,
    "Group2_4": 145,
    "Group2_5": 70,
    "Group2_6": 224,
    "Group2_7": 261,
    "Group2_8": 38,
    "Header_1": 175,
    "Header_2": 243,
    "Host": 0,
    "Icon1": 52,
    "icon2": 12,
    "Icon2": 16,
    "icon2_1": 107,
    "Icon2_1": 131,
    "icon2_2": 86,
    "Icon2_2": 89,
    "icon2_3": 128,
    "Icon2_3": 110,
    "icon2_4": 144,
    "Icon2_4": 72,
    "icon2_5": 69,
    "Icon2_5": 226,
    "icon2_6": 223,
    "Icon2_6": 263,
    "icon2_7": 259,
    "Icon2_7": 43,
    "icon2_8": 39,
    "icon3": 98,
    "Icon3": 33,
    "icon3_1": 272,
    "Icon3_1": 283,
    "Icon3_2": 63,
    "Icon5": 164,
    "Image1": 0,
    "Image2": 21,
    "Image3": 160,
    "Label1": 3,
    "Label1_1": 6,
    "Label10": 29,
    "Label10_1": 32,
    "Label10_2": 34,
    "Label10_3": 279,
    "Label10_4": 282,
    "Label10_5": 284,
    "Label10_6": 59,
    "Label10_7": 62,
    "Label10_8": 64,
    "Label11": 162,
    "Label12": 22,
    "Label13": 23,
    "Label14": 163,
    "Label16": 99,
    "Label16_1": 271,
    "Label16_2": 50,
    "Label17": 100,
    "Label17_1": 273,
    "Label17_2": 51,
    "Label18": 101,
    "Label2": 94,
    "Label2_1": 170,
    "Label2_2": 159,
    "Label2_4": 165,
    "Label3": 136,
    "Label3_1": 77,
    "Label4": 30,
    "Label4_1": 280,
    "Label4_10": 155,
    "Label4_11": 154,
    "Label4_2": 60,
    "Label4_7": 156,
    "Label4_9": 153,
    "Label5": 139,
    "Label5_1": 140,
    "Label5_2": 80,
    "Label5_3": 81,
    "Label6": 198,
    "Label9_10": 46,
    "Label9_2": 135,
    "Label9_3": 114,
    "Label9_4": 148,
    "Label9_5": 76,
    "Label9_6": 230,
    "Label9_7": 93,
    "Label9_8": 19,
    "Label9_9": 267,
    "LblHeaderCreateNew": 13,
    "LblHeaderCreateNew_1": 106,
    "LblHeaderCreateNew_2": 85,
    "LblHeaderCreateNew_3": 127,
    "LblHeaderCreateNew_4": 68,
    "LblHeaderCreateNew_5": 222,
    "LblHeaderCreateNew_6": 260,
    "LblHeaderCreateNew_7": 40,
    "LblHeaderTItle1": 9,
    "LblHeaderTItle1_1": 10,
    "LblHeaderTItle1_10": 66,
    "LblHeaderTItle1_11": 67,
    "LblHeaderTItle1_12": 220,
    "LblHeaderTItle1_13": 221,
    "LblHeaderTItle1_14": 257,
    "LblHeaderTItle1_15": 258,
    "LblHeaderTItle1_16": 36,
    "LblHeaderTItle1_17": 37,
    "LblHeaderTItle1_2": 104,
    "LblHeaderTItle1_3": 105,
    "LblHeaderTItle1_4": 83,
    "LblHeaderTItle1_5": 84,
    "LblHeaderTItle1_6": 125,
    "LblHeaderTItle1_7": 126,
    "LblHeaderTItle1_8": 142,
    "LblHeaderTItle1_9": 143,
    "LeaveDescription_DataCard2": 192,
    "LeaveStatus_DataCard2": 207,
    "LeaveType_DataCard2": 177,
    "LoginScreen": 86,
    "ManagerRequests": 95,
    "MyLeaveBalance": 121,
    "MyLeaveRequests": 142,
    "MyLeaveRequests_1": 170,
    "MyLeaveRequests_2": 200,
    "NewExpenseCancelButton_1": 254,
    "NewExpenseCreateButton_2": 255,
    "NewRequestLabel_1": 174,
    "NewRequestLabel_2": 242,
    "NewRequests_1": 229,
    "Popup Confirmation_1": 167,
    "popup rectangle_1": 168,
    "Rectangle1_1": 166,
    "Rectangle1_2": 240,
    "Rectangle2_1": 169,
    "Rectangle6": 97,
    "Rectangle6_1": 270,
    "Rectangle6_2": 49,
    "Screen1": 282,
    "Screen2": 299,
    "StartDate_DataCard2": 182,
    "StarVisible1": 213,
    "StarVisible11": 188,
    "StarVisible13": 193,
    "StarVisible2": 200,
    "StarVisible5": 208,
    "StarVisible6": 178,
    "StarVisible9": 183,
    "SubmitForm_1": 171
  },
  "ResourcesJsonIndices": {
    "Image-IMAGE1": 1,
    "Image-image2": 2,
    "Image-LMS": 3,
    "Image-SampleImage": 0
  },
  "RuleScreenIdWithoutScreen": {},
  "TemplateVersions": {},
  "VolatileProperties": {
    "AnalysisLoadTime": 1.2726301,
    "ControlCount": {
      "9c778db04d854105b4af47ae39f6462e": 1,
      "button": 17,
      "circle": 8,
      "combobox": 3,
      "datepicker": 4,
      "dropdown": 1,
      "form": 1,
      "gallery": 24,
      "galleryTemplate": 24,
      "group": 22,
      "groupContainer": 15,
      "icon": 25,
      "image": 3,
      "label": 113,
      "rectangle": 10,
      "screen": 13,
      "text": 4,
      "typedDataCard": 9
    },
    "DeserializationLoadTime": 4.7550827
  },
  "WasLocalDatabaseReferencesEmpty": true
}